fonetika/__init__.py
fonetika/base.py
fonetika/config.py
fonetika/distance.py
fonetika/metaphone.py
fonetika/soundex.py
fonetika/base/__init__.py
fonetika/base/base.py
fonetika-1.2.0.dist-info/LICENSE
fonetika-1.2.0.dist-info/METADATA
fonetika-1.2.0.dist-info/WHEEL
fonetika-1.2.0.dist-info/top_level.txt
fonetika-1.2.0.dist-info/RECORD
