Metadata-Version: 2.1
Name: fonetika
Version: 1.2.0
Summary: Phonetics algorithms (Soundex and Metaphone) for russian, english, finnish and estonian languages
Home-page: https://github.com/roddar92/russian_soundex
Author: Daria Rodionova
Author-email: drodionova86@gmail.com
License: MIT
Platform: UNKNOWN
Classifier: Intended Audience :: Developers
Classifier: Intended Audience :: Science/Research
Classifier: Natural Language :: Russian
Classifier: Natural Language :: Finnish
Classifier: Topic :: Text Processing :: Linguistic
Requires-Dist: pymorphy2
Requires-Dist: editdistance
